mojipack/__init__.py
mojipack/codec.py
mojipack/default_byte_mapping.py
mojipack-2.0.0.dist-info/LICENCE
mojipack-2.0.0.dist-info/METADATA
mojipack-2.0.0.dist-info/WHEEL
mojipack-2.0.0.dist-info/top_level.txt
mojipack-2.0.0.dist-info/RECORD
