Metadata-Version: 2.1
Name: mojipack
Version: 2.0.0
Summary: Encode binary data into fun emoji strings!
Author-email: BrinkerVII <brinkervii@gmail.com>
Project-URL: homepage, https://gitlab.com/brinkervii/mojipack
Project-URL: repository, https://gitlab.com/brinkervii/mojipack
Keywords: emoji,encoding
Classifier: Development Status :: 5 - Production/Stable
Classifier: Programming Language :: Python :: 3.8
Classifier: Programming Language :: Python :: 3.9
Classifier: Programming Language :: Python :: 3.10
Classifier: Programming Language :: Python :: 3.11
Requires-Python: >=3.8
License-File: LICENCE
Requires-Dist: emoji >=2.7.0
Requires-Dist: cryptography >=41.0.0
Provides-Extra: dev
Requires-Dist: pytest ; extra == 'dev'
Requires-Dist: msgpack ; extra == 'dev'
Requires-Dist: build ; extra == 'dev'
Requires-Dist: twine ; extra == 'dev'
Requires-Dist: pylint ; extra == 'dev'
